[
  {
    "cateogary": "Literate without educational level",
    "cateogarySum": 2809137
  },
  {
    "cateogary": "Below Primary",
    "cateogarySum": 14093454
  },
  {
    "cateogary": "Primary - Persons",
    "cateogarySum": 17761260
  },
  {
    "cateogary": "Educational level - Middle",
    "cateogarySum": 13291427
  },
  {
    "cateogary": "Educational level - Matric/Secondary",
    "cateogarySum": 8283421
  },
  {
    "cateogary": "Educational level - Higher secondary",
    "cateogarySum": 5593844
  },
  {
    "cateogary": "Educational level - Non-technical diploma",
    "cateogarySum": 51704
  },
  {
    "cateogary": "Educational level - Technical diploma",
    "cateogarySum": 583859
  },
  {
    "cateogary": "Graduate & above ",
    "cateogarySum": 3751759
  },
  {
    "cateogary": "Unclassified",
    "cateogarySum": 257099
  }
]